README.md
setup.py
slack_actions/__init__.py
slack_actions/api.py
slack_actions/slack_controller.py
slack_actions.egg-info/PKG-INFO
slack_actions.egg-info/SOURCES.txt
slack_actions.egg-info/dependency_links.txt
slack_actions.egg-info/requires.txt
slack_actions.egg-info/top_level.txt